{
  "analysis": {
    "marketTrend": "BTC 当前价格在 91428 USDT 附近震荡，1小时 K线显示价格在 91000-91847 区间波动，短期呈现震荡整理格局。5分钟 K线显示价格在 91389-91517 窄幅波动，缺乏明确方向。订单簿卖盘深度显著高于买盘（买卖比 0.25），显示上方存在较大抛压。",
    "positionStatus": "当前持有多仓（持仓价 91226.5 USDT，浮盈 0.22%）和空仓（持仓价 90669.9 USDT，浮亏 0.84%），多空仓位数量相同但盈亏失衡。总未实现亏损 -2.78 USDT，空仓亏损需要重点关注。",
    "riskAssessment": "账户余额充足（949.95 USDT可用），保证金使用率 0%，实际杠杆率 0.96x，风险等级 LOW，具备补仓空间但当前无需干预。"
  },
  "signal": {
    "action": "HOLD",
    "confidence": "MEDIUM",
    "reasoning": "市场处于震荡阶段且多空力量相对平衡，现有持仓亏损幅度未达补仓阈值（-3%）。卖盘深度压制上涨空间但未形成破位，建议保持观望等待明确趋势信号。"
  },
  "execution": {
    "hasOrder": false,
    "orders": []
  },
  "riskWarning": "卖盘累积可能引发价格回调，需关注 91500 关键阻力位突破情况。"
}